{"id": "texttiling-w18-k8-m+0.75-n2-s4", "items": {"interviews:U-0005": {"TextTiling-w18-k8-m+0.75-n2-s4": [394, 437, 326]}, "interviews:U-0007": {"TextTiling-w18-k8-m+0.75-n2-s4": [101, 106, 382]}, "interviews:U-0008": {"TextTiling-w18-k8-m+0.75-n2-s4": [63, 375, 254]}, "interviews:U-0011": {"TextTiling-w18-k8-m+0.75-n2-s4": [105]}, "interviews:U-0012": {"TextTiling-w18-k8-m+0.75-n2-s4": [135, 216, 136]}, "interviews:U-0014": {"TextTiling-w18-k8-m+0.75-n2-s4": [93, 310, 378]}, "interviews:U-0017": {"TextTiling-w18-k8-m+0.75-n2-s4": [74, 105, 609]}, "interviews:U-0019": {"TextTiling-w18-k8-m+0.75-n2-s4": [297, 72, 128, 128, 90, 177, 222]}, "interviews:U-0020": {"TextTiling-w18-k8-m+0.75-n2-s4": [491, 260, 180]}, "interviews:U-0023": {"TextTiling-w18-k8-m+0.75-n2-s4": [59, 402, 423]}, "interviews:U-0098": {"TextTiling-w18-k8-m+0.75-n2-s4": [295, 524, 509]}, "interviews:U-0178": {"TextTiling-w18-k8-m+0.75-n2-s4": [154, 138, 520]}, "interviews:U-0180": {"TextTiling-w18-k8-m+0.75-n2-s4": [232, 88, 242, 73, 426]}, "interviews:U-0181": {"TextTiling-w18-k8-m+0.75-n2-s4": [409, 761, 352]}, "interviews:U-0183": {"TextTiling-w18-k8-m+0.75-n2-s4": [169, 277, 129, 843, 217]}, "interviews:U-0184": {"TextTiling-w18-k8-m+0.75-n2-s4": [270, 171, 205]}, "interviews:U-0185": {"TextTiling-w18-k8-m+0.75-n2-s4": [127, 236, 64]}, "interviews:U-0186": {"TextTiling-w18-k8-m+0.75-n2-s4": [121, 135, 276]}, "interviews:U-0193": {"TextTiling-w18-k8-m+0.75-n2-s4": [945]}}, "segmentation_type": "linear"}
