{"id": "texttiling-w26-k14-m+0.00-n3-s3", "items": {"interviews:U-0005": {"TextTiling-w26-k14-m+0.00-n3-s3": [229, 192, 736]}, "interviews:U-0007": {"TextTiling-w26-k14-m+0.00-n3-s3": [182, 83, 324]}, "interviews:U-0008": {"TextTiling-w26-k14-m+0.00-n3-s3": [157, 127, 408]}, "interviews:U-0011": {"TextTiling-w26-k14-m+0.00-n3-s3": [105]}, "interviews:U-0012": {"TextTiling-w26-k14-m+0.00-n3-s3": [487]}, "interviews:U-0014": {"TextTiling-w26-k14-m+0.00-n3-s3": [206, 385, 190]}, "interviews:U-0017": {"TextTiling-w26-k14-m+0.00-n3-s3": [163, 67, 558]}, "interviews:U-0019": {"TextTiling-w26-k14-m+0.00-n3-s3": [339, 202, 168, 170, 235]}, "interviews:U-0020": {"TextTiling-w26-k14-m+0.00-n3-s3": [342, 165, 95, 60, 269]}, "interviews:U-0023": {"TextTiling-w26-k14-m+0.00-n3-s3": [126, 118, 204, 119, 317]}, "interviews:U-0098": {"TextTiling-w26-k14-m+0.00-n3-s3": [268, 173, 353, 88, 446]}, "interviews:U-0178": {"TextTiling-w26-k14-m+0.00-n3-s3": [128, 164, 520]}, "interviews:U-0180": {"TextTiling-w26-k14-m+0.00-n3-s3": [116, 129, 63, 54, 92, 157, 450]}, "interviews:U-0181": {"TextTiling-w26-k14-m+0.00-n3-s3": [386, 365, 771]}, "interviews:U-0183": {"TextTiling-w26-k14-m+0.00-n3-s3": [237, 407, 991]}, "interviews:U-0184": {"TextTiling-w26-k14-m+0.00-n3-s3": [261, 150, 235]}, "interviews:U-0185": {"TextTiling-w26-k14-m+0.00-n3-s3": [123, 155, 149]}, "interviews:U-0186": {"TextTiling-w26-k14-m+0.00-n3-s3": [243, 119, 170]}, "interviews:U-0193": {"TextTiling-w26-k14-m+0.00-n3-s3": [99, 265, 581]}}, "segmentation_type": "linear"}
