{"id": "texttiling-w24-k14-m-0.50-n1-s4", "items": {"interviews:U-0005": {"TextTiling-w24-k14-m-0.50-n1-s4": [100, 153, 33, 155, 123, 73, 85, 32, 108, 147, 148]}, "interviews:U-0007": {"TextTiling-w24-k14-m-0.50-n1-s4": [106, 106, 85, 87, 205]}, "interviews:U-0008": {"TextTiling-w24-k14-m-0.50-n1-s4": [42, 57, 74, 133, 38, 99, 249]}, "interviews:U-0011": {"TextTiling-w24-k14-m-0.50-n1-s4": [105]}, "interviews:U-0012": {"TextTiling-w24-k14-m-0.50-n1-s4": [69, 65, 128, 88, 137]}, "interviews:U-0014": {"TextTiling-w24-k14-m-0.50-n1-s4": [102, 67, 62, 52, 176, 161, 161]}, "interviews:U-0017": {"TextTiling-w24-k14-m-0.50-n1-s4": [116, 71, 69, 205, 327]}, "interviews:U-0019": {"TextTiling-w24-k14-m-0.50-n1-s4": [63, 226, 63, 17, 133, 60, 58, 54, 55, 112, 273]}, "interviews:U-0020": {"TextTiling-w24-k14-m-0.50-n1-s4": [223, 73, 66, 127, 42, 90, 60, 81, 169]}, "interviews:U-0023": {"TextTiling-w24-k14-m-0.50-n1-s4": [59, 81, 45, 72, 201, 21, 114, 29, 35, 56, 171]}, "interviews:U-0098": {"TextTiling-w24-k14-m-0.50-n1-s4": [197, 105, 68, 90, 73, 151, 137, 82, 425]}, "interviews:U-0178": {"TextTiling-w24-k14-m-0.50-n1-s4": [82, 71, 73, 22, 64, 120, 67, 37, 66, 8, 202]}, "interviews:U-0180": {"TextTiling-w24-k14-m-0.50-n1-s4": [142, 126, 58, 61, 86, 164, 9, 61, 52, 63, 239]}, "interviews:U-0181": {"TextTiling-w24-k14-m-0.50-n1-s4": [100, 62, 246, 318, 58, 177, 78, 135, 348]}, "interviews:U-0183": {"TextTiling-w24-k14-m-0.50-n1-s4": [171, 94, 205, 104, 95, 258, 213, 91, 164, 31, 209]}, "interviews:U-0184": {"TextTiling-w24-k14-m-0.50-n1-s4": [116, 152, 67, 106, 205]}, "interviews:U-0185": {"TextTiling-w24-k14-m-0.50-n1-s4": [72, 67, 288]}, "interviews:U-0186": {"TextTiling-w24-k14-m-0.50-n1-s4": [77, 46, 42, 68, 29, 120, 150]}, "interviews:U-0193": {"TextTiling-w24-k14-m-0.50-n1-s4": [122, 111, 148, 130, 120, 52, 262]}}, "segmentation_type": "linear"}
