{"id": "texttiling-w18-k6-m+0.25-n4-s4", "items": {"interviews:U-0005": {"TextTiling-w18-k6-m+0.25-n4-s4": [359, 211, 587]}, "interviews:U-0007": {"TextTiling-w18-k6-m+0.25-n4-s4": [87, 72, 430]}, "interviews:U-0008": {"TextTiling-w18-k6-m+0.25-n4-s4": [120, 165, 407]}, "interviews:U-0011": {"TextTiling-w18-k6-m+0.25-n4-s4": [105]}, "interviews:U-0012": {"TextTiling-w18-k6-m+0.25-n4-s4": [65, 50, 372]}, "interviews:U-0014": {"TextTiling-w18-k6-m+0.25-n4-s4": [45, 330, 406]}, "interviews:U-0017": {"TextTiling-w18-k6-m+0.25-n4-s4": [46, 101, 641]}, "interviews:U-0019": {"TextTiling-w18-k6-m+0.25-n4-s4": [276, 250, 588]}, "interviews:U-0020": {"TextTiling-w18-k6-m+0.25-n4-s4": [188, 282, 181, 86, 194]}, "interviews:U-0023": {"TextTiling-w18-k6-m+0.25-n4-s4": [48, 385, 180, 135, 136]}, "interviews:U-0098": {"TextTiling-w18-k6-m+0.25-n4-s4": [244, 283, 801]}, "interviews:U-0178": {"TextTiling-w18-k6-m+0.25-n4-s4": [123, 149, 540]}, "interviews:U-0180": {"TextTiling-w18-k6-m+0.25-n4-s4": [195, 107, 228, 76, 163, 98, 194]}, "interviews:U-0181": {"TextTiling-w18-k6-m+0.25-n4-s4": [388, 358, 776]}, "interviews:U-0183": {"TextTiling-w18-k6-m+0.25-n4-s4": [144, 390, 1101]}, "interviews:U-0184": {"TextTiling-w18-k6-m+0.25-n4-s4": [226, 180, 240]}, "interviews:U-0185": {"TextTiling-w18-k6-m+0.25-n4-s4": [113, 102, 212]}, "interviews:U-0186": {"TextTiling-w18-k6-m+0.25-n4-s4": [109, 135, 288]}, "interviews:U-0193": {"TextTiling-w18-k6-m+0.25-n4-s4": [88, 168, 689]}}, "segmentation_type": "linear"}
