{"id": "texttiling-w18-k6-m+1.00-n4-s1-projected-onto-speakers", "items": {"interviews:U-0005": {"TextTiling-w18-k6-m+1.00-n4-s1": [15, 79, 72, 52, 30]}, "interviews:U-0007": {"TextTiling-w18-k6-m+1.00-n4-s1": [4, 47, 14, 5, 83]}, "interviews:U-0008": {"TextTiling-w18-k6-m+1.00-n4-s1": [5, 9, 66]}, "interviews:U-0011": {"TextTiling-w18-k6-m+1.00-n4-s1": [25]}, "interviews:U-0012": {"TextTiling-w18-k6-m+1.00-n4-s1": [3, 5, 107]}, "interviews:U-0014": {"TextTiling-w18-k6-m+1.00-n4-s1": [46, 8, 76, 81, 34]}, "interviews:U-0017": {"TextTiling-w18-k6-m+1.00-n4-s1": [44, 13, 66]}, "interviews:U-0019": {"TextTiling-w18-k6-m+1.00-n4-s1": [12, 24, 4, 20, 3, 3, 37]}, "interviews:U-0020": {"TextTiling-w18-k6-m+1.00-n4-s1": [33, 55, 20, 9, 28]}, "interviews:U-0023": {"TextTiling-w18-k6-m+1.00-n4-s1": [11, 16, 9, 78, 112]}, "interviews:U-0098": {"TextTiling-w18-k6-m+1.00-n4-s1": [214, 25, 41, 57, 226]}, "interviews:U-0178": {"TextTiling-w18-k6-m+1.00-n4-s1": [23, 8, 13, 35, 81]}, "interviews:U-0180": {"TextTiling-w18-k6-m+1.00-n4-s1": [83, 86, 76]}, "interviews:U-0181": {"TextTiling-w18-k6-m+1.00-n4-s1": [32, 39, 73, 2, 19, 8, 39]}, "interviews:U-0183": {"TextTiling-w18-k6-m+1.00-n4-s1": [41, 42, 28, 26, 138]}, "interviews:U-0184": {"TextTiling-w18-k6-m+1.00-n4-s1": [60, 43, 17]}, "interviews:U-0185": {"TextTiling-w18-k6-m+1.00-n4-s1": [42, 69, 33]}, "interviews:U-0186": {"TextTiling-w18-k6-m+1.00-n4-s1": [24, 5, 15, 34, 18]}, "interviews:U-0193": {"TextTiling-w18-k6-m+1.00-n4-s1": [4, 11, 24, 15, 45]}}, "segmentation_type": "linear"}
