{"id": "texttiling-w14-k8-m+0.50-n2-s2-projected-onto-speakers", "items": {"interviews:U-0005": {"TextTiling-w14-k8-m+0.50-n2-s2": [6, 9, 69, 10, 18, 4, 27, 27, 78]}, "interviews:U-0007": {"TextTiling-w14-k8-m+0.50-n2-s2": [5, 20, 26, 15, 87]}, "interviews:U-0008": {"TextTiling-w14-k8-m+0.50-n2-s2": [2, 3, 10, 14, 15, 36]}, "interviews:U-0011": {"TextTiling-w14-k8-m+0.50-n2-s2": [25]}, "interviews:U-0012": {"TextTiling-w14-k8-m+0.50-n2-s2": [3, 6, 36, 32, 38]}, "interviews:U-0014": {"TextTiling-w14-k8-m+0.50-n2-s2": [46, 8, 72, 4, 32, 50, 33]}, "interviews:U-0017": {"TextTiling-w14-k8-m+0.50-n2-s2": [19, 10, 16, 12, 16, 19, 31]}, "interviews:U-0019": {"TextTiling-w14-k8-m+0.50-n2-s2": [12, 24, 4, 16, 5, 2, 3, 1, 11, 6, 19]}, "interviews:U-0020": {"TextTiling-w14-k8-m+0.50-n2-s2": [13, 75, 7, 14, 8, 13, 15]}, "interviews:U-0023": {"TextTiling-w14-k8-m+0.50-n2-s2": [28, 8, 52, 7, 17, 25, 11, 33, 23, 7, 15]}, "interviews:U-0098": {"TextTiling-w14-k8-m+0.50-n2-s2": [167, 33, 14, 25, 44, 60, 68, 35, 117]}, "interviews:U-0178": {"TextTiling-w14-k8-m+0.50-n2-s2": [1, 22, 8, 13, 35, 28, 53]}, "interviews:U-0180": {"TextTiling-w14-k8-m+0.50-n2-s2": [20, 65, 27, 22, 12, 23, 4, 21, 51]}, "interviews:U-0181": {"TextTiling-w14-k8-m+0.50-n2-s2": [32, 4, 36, 7, 56, 9, 2, 19, 47]}, "interviews:U-0183": {"TextTiling-w14-k8-m+0.50-n2-s2": [41, 39, 31, 27, 25, 31, 81]}, "interviews:U-0184": {"TextTiling-w14-k8-m+0.50-n2-s2": [61, 14, 10, 18, 17]}, "interviews:U-0185": {"TextTiling-w14-k8-m+0.50-n2-s2": [42, 45, 25, 16, 16]}, "interviews:U-0186": {"TextTiling-w14-k8-m+0.50-n2-s2": [8, 17, 4, 7, 8, 23, 5, 7, 17]}, "interviews:U-0193": {"TextTiling-w14-k8-m+0.50-n2-s2": [4, 9, 2, 18, 6, 14, 1, 25, 20]}}, "segmentation_type": "linear"}
