{"id": "texttiling-w14-k10-m+0.25-n1-s4", "items": {"interviews:U-0005": {"TextTiling-w14-k10-m+0.25-n1-s4": [117, 200, 47, 59, 85, 64, 77, 86, 46, 241, 135]}, "interviews:U-0007": {"TextTiling-w14-k10-m+0.25-n1-s4": [111, 8, 111, 54, 37, 69, 199]}, "interviews:U-0008": {"TextTiling-w14-k10-m+0.25-n1-s4": [33, 24, 14, 22, 69, 42, 35, 64, 59, 32, 298]}, "interviews:U-0011": {"TextTiling-w14-k10-m+0.25-n1-s4": [105]}, "interviews:U-0012": {"TextTiling-w14-k10-m+0.25-n1-s4": [32, 41, 77, 116, 221]}, "interviews:U-0014": {"TextTiling-w14-k10-m+0.25-n1-s4": [114, 54, 61, 69, 131, 80, 39, 140, 93]}, "interviews:U-0017": {"TextTiling-w14-k10-m+0.25-n1-s4": [74, 30, 87, 79, 89, 124, 305]}, "interviews:U-0019": {"TextTiling-w14-k10-m+0.25-n1-s4": [89, 46, 40, 53, 68, 24, 78, 112, 60, 69, 35, 53, 387]}, "interviews:U-0020": {"TextTiling-w14-k10-m+0.25-n1-s4": [105, 54, 82, 44, 42, 35, 48, 87, 51, 39, 47, 35, 89, 9, 164]}, "interviews:U-0023": {"TextTiling-w14-k10-m+0.25-n1-s4": [68, 28, 57, 33, 36, 134, 100, 22, 78, 43, 30, 29, 57, 69, 100]}, "interviews:U-0098": {"TextTiling-w14-k10-m+0.25-n1-s4": [44, 273, 61, 50, 42, 60, 149, 157, 86, 77, 78, 138, 113]}, "interviews:U-0178": {"TextTiling-w14-k10-m+0.25-n1-s4": [35, 46, 85, 68, 37, 34, 27, 56, 68, 151, 77, 51, 77]}, "interviews:U-0180": {"TextTiling-w14-k10-m+0.25-n1-s4": [62, 155, 107, 125, 46, 91, 63, 63, 118, 140, 91]}, "interviews:U-0181": {"TextTiling-w14-k10-m+0.25-n1-s4": [94, 90, 55, 186, 98, 152, 122, 75, 36, 54, 41, 37, 87, 78, 317]}, "interviews:U-0183": {"TextTiling-w14-k10-m+0.25-n1-s4": [187, 18, 145, 118, 140, 180, 174, 71, 45, 153, 146, 65, 193]}, "interviews:U-0184": {"TextTiling-w14-k10-m+0.25-n1-s4": [124, 145, 103, 99, 175]}, "interviews:U-0185": {"TextTiling-w14-k10-m+0.25-n1-s4": [137, 172, 118]}, "interviews:U-0186": {"TextTiling-w14-k10-m+0.25-n1-s4": [44, 42, 46, 35, 14, 25, 58, 128, 27, 28, 85]}, "interviews:U-0193": {"TextTiling-w14-k10-m+0.25-n1-s4": [36, 101, 119, 88, 135, 38, 277, 44, 107]}}, "segmentation_type": "linear"}
