{"id": "texttiling-w22-k6-m+0.00-n1-s3", "items": {"interviews:U-0005": {"TextTiling-w22-k6-m+0.00-n1-s3": [114, 303, 153, 75, 90, 44, 83, 199, 96]}, "interviews:U-0007": {"TextTiling-w22-k6-m+0.00-n1-s3": [119, 101, 84, 15, 68, 66, 136]}, "interviews:U-0008": {"TextTiling-w22-k6-m+0.00-n1-s3": [31, 39, 21, 71, 39, 58, 44, 57, 332]}, "interviews:U-0011": {"TextTiling-w22-k6-m+0.00-n1-s3": [105]}, "interviews:U-0012": {"TextTiling-w22-k6-m+0.00-n1-s3": [28, 45, 52, 53, 93, 91, 125]}, "interviews:U-0014": {"TextTiling-w22-k6-m+0.00-n1-s3": [112, 52, 63, 66, 131, 90, 23, 150, 94]}, "interviews:U-0017": {"TextTiling-w22-k6-m+0.00-n1-s3": [83, 20, 86, 73, 88, 124, 314]}, "interviews:U-0019": {"TextTiling-w22-k6-m+0.00-n1-s3": [90, 44, 40, 50, 71, 22, 80, 105, 66, 71, 36, 56, 110, 45, 228]}, "interviews:U-0020": {"TextTiling-w22-k6-m+0.00-n1-s3": [222, 18, 40, 108, 109, 48, 87, 42, 87, 88, 82]}, "interviews:U-0023": {"TextTiling-w22-k6-m+0.00-n1-s3": [102, 49, 40, 30, 136, 99, 17, 79, 47, 32, 25, 56, 58, 14, 100]}, "interviews:U-0098": {"TextTiling-w22-k6-m+0.00-n1-s3": [246, 64, 66, 48, 40, 68, 147, 156, 85, 79, 329]}, "interviews:U-0178": {"TextTiling-w22-k6-m+0.00-n1-s3": [92, 59, 51, 102, 151, 144, 213]}, "interviews:U-0180": {"TextTiling-w22-k6-m+0.00-n1-s3": [54, 64, 105, 102, 165, 90, 66, 68, 72, 43, 75, 60, 97]}, "interviews:U-0181": {"TextTiling-w22-k6-m+0.00-n1-s3": [102, 80, 46, 9, 171, 7, 100, 145, 132, 115, 99, 32, 87, 66, 331]}, "interviews:U-0183": {"TextTiling-w22-k6-m+0.00-n1-s3": [112, 76, 79, 87, 117, 135, 181, 178, 101, 367, 202]}, "interviews:U-0184": {"TextTiling-w22-k6-m+0.00-n1-s3": [54, 65, 72, 81, 100, 88, 186]}, "interviews:U-0185": {"TextTiling-w22-k6-m+0.00-n1-s3": [139, 103, 67, 62, 56]}, "interviews:U-0186": {"TextTiling-w22-k6-m+0.00-n1-s3": [43, 44, 37, 9, 44, 29, 58, 27, 99, 29, 113]}, "interviews:U-0193": {"TextTiling-w22-k6-m+0.00-n1-s3": [39, 23, 71, 157, 52, 175, 164, 110, 154]}}, "segmentation_type": "linear"}
