{"id": "texttiling-w24-k6-m+1.00-n1-s1", "items": {"interviews:U-0005": {"TextTiling-w24-k6-m+1.00-n1-s1": [125, 241, 57, 314, 420]}, "interviews:U-0007": {"TextTiling-w24-k6-m+1.00-n1-s1": [236, 57, 296]}, "interviews:U-0008": {"TextTiling-w24-k6-m+1.00-n1-s1": [38, 37, 617]}, "interviews:U-0011": {"TextTiling-w24-k6-m+1.00-n1-s1": [105]}, "interviews:U-0012": {"TextTiling-w24-k6-m+1.00-n1-s1": [33, 43, 411]}, "interviews:U-0014": {"TextTiling-w24-k6-m+1.00-n1-s1": [123, 60, 255, 260, 83]}, "interviews:U-0017": {"TextTiling-w24-k6-m+1.00-n1-s1": [81, 115, 592]}, "interviews:U-0019": {"TextTiling-w24-k6-m+1.00-n1-s1": [100, 203, 22, 184, 62, 74, 40, 44, 385]}, "interviews:U-0020": {"TextTiling-w24-k6-m+1.00-n1-s1": [366, 134, 139, 29, 263]}, "interviews:U-0023": {"TextTiling-w24-k6-m+1.00-n1-s1": [154, 70, 383, 25, 252]}, "interviews:U-0098": {"TextTiling-w24-k6-m+1.00-n1-s1": [336, 96, 55, 46, 151, 166, 478]}, "interviews:U-0178": {"TextTiling-w24-k6-m+1.00-n1-s1": [20, 20, 204, 27, 41, 261, 37, 130, 72]}, "interviews:U-0180": {"TextTiling-w24-k6-m+1.00-n1-s1": [66, 160, 277, 93, 60, 61, 118, 136, 90]}, "interviews:U-0181": {"TextTiling-w24-k6-m+1.00-n1-s1": [100, 90, 723, 98, 511]}, "interviews:U-0183": {"TextTiling-w24-k6-m+1.00-n1-s1": [187, 173, 122, 140, 344, 121, 548]}, "interviews:U-0184": {"TextTiling-w24-k6-m+1.00-n1-s1": [268, 110, 268]}, "interviews:U-0185": {"TextTiling-w24-k6-m+1.00-n1-s1": [139, 171, 117]}, "interviews:U-0186": {"TextTiling-w24-k6-m+1.00-n1-s1": [44, 43, 49, 48, 81, 184, 83]}, "interviews:U-0193": {"TextTiling-w24-k6-m+1.00-n1-s1": [40, 104, 203, 453, 145]}}, "segmentation_type": "linear"}
