{"id": "texttiling-w16-k10-m+0.50-n4-s1", "items": {"interviews:U-0005": {"TextTiling-w16-k10-m+0.50-n4-s1": [118, 245, 50, 236, 80, 52, 376]}, "interviews:U-0007": {"TextTiling-w16-k10-m+0.50-n4-s1": [228, 57, 31, 74, 199]}, "interviews:U-0008": {"TextTiling-w16-k10-m+0.50-n4-s1": [33, 38, 23, 107, 491]}, "interviews:U-0011": {"TextTiling-w16-k10-m+0.50-n4-s1": [105]}, "interviews:U-0012": {"TextTiling-w16-k10-m+0.50-n4-s1": [29, 43, 415]}, "interviews:U-0014": {"TextTiling-w16-k10-m+0.50-n4-s1": [115, 52, 265, 74, 41, 141, 93]}, "interviews:U-0017": {"TextTiling-w16-k10-m+0.50-n4-s1": [74, 113, 601]}, "interviews:U-0019": {"TextTiling-w16-k10-m+0.50-n4-s1": [89, 44, 96, 60, 32, 177, 70, 67, 39, 48, 392]}, "interviews:U-0020": {"TextTiling-w16-k10-m+0.50-n4-s1": [361, 136, 136, 124, 174]}, "interviews:U-0023": {"TextTiling-w16-k10-m+0.50-n4-s1": [68, 84, 33, 36, 233, 25, 115, 33, 257]}, "interviews:U-0098": {"TextTiling-w16-k10-m+0.50-n4-s1": [53, 185, 87, 49, 55, 43, 207, 160, 489]}, "interviews:U-0178": {"TextTiling-w16-k10-m+0.50-n4-s1": [33, 64, 111, 59, 545]}, "interviews:U-0180": {"TextTiling-w16-k10-m+0.50-n4-s1": [60, 160, 102, 172, 92, 61, 67, 115, 232]}, "interviews:U-0181": {"TextTiling-w16-k10-m+0.50-n4-s1": [90, 93, 35, 27, 555, 73, 35, 55, 39, 37, 483]}, "interviews:U-0183": {"TextTiling-w16-k10-m+0.50-n4-s1": [171, 297, 140, 179, 172, 73, 43, 154, 406]}, "interviews:U-0184": {"TextTiling-w16-k10-m+0.50-n4-s1": [54, 66, 526]}, "interviews:U-0185": {"TextTiling-w16-k10-m+0.50-n4-s1": [137, 171, 119]}, "interviews:U-0186": {"TextTiling-w16-k10-m+0.50-n4-s1": [42, 40, 47, 38, 97, 128, 28, 26, 86]}, "interviews:U-0193": {"TextTiling-w16-k10-m+0.50-n4-s1": [34, 102, 208, 172, 278, 44, 107]}}, "segmentation_type": "linear"}
