{"id": "texttiling-w22-k14-m+0.50-n3-s3", "items": {"interviews:U-0005": {"TextTiling-w22-k14-m+0.50-n3-s3": [75, 168, 914]}, "interviews:U-0007": {"TextTiling-w22-k14-m+0.50-n3-s3": [192, 85, 312]}, "interviews:U-0008": {"TextTiling-w22-k14-m+0.50-n3-s3": [153, 138, 401]}, "interviews:U-0011": {"TextTiling-w22-k14-m+0.50-n3-s3": [105]}, "interviews:U-0012": {"TextTiling-w22-k14-m+0.50-n3-s3": [487]}, "interviews:U-0014": {"TextTiling-w22-k14-m+0.50-n3-s3": [83, 517, 181]}, "interviews:U-0017": {"TextTiling-w22-k14-m+0.50-n3-s3": [176, 63, 549]}, "interviews:U-0019": {"TextTiling-w22-k14-m+0.50-n3-s3": [340, 372, 402]}, "interviews:U-0020": {"TextTiling-w22-k14-m+0.50-n3-s3": [348, 166, 93, 141, 183]}, "interviews:U-0023": {"TextTiling-w22-k14-m+0.50-n3-s3": [884]}, "interviews:U-0098": {"TextTiling-w22-k14-m+0.50-n3-s3": [344, 104, 352, 87, 441]}, "interviews:U-0178": {"TextTiling-w22-k14-m+0.50-n3-s3": [67, 72, 673]}, "interviews:U-0180": {"TextTiling-w22-k14-m+0.50-n3-s3": [314, 54, 693]}, "interviews:U-0181": {"TextTiling-w22-k14-m+0.50-n3-s3": [388, 375, 263, 129, 367]}, "interviews:U-0183": {"TextTiling-w22-k14-m+0.50-n3-s3": [154, 83, 409, 743, 246]}, "interviews:U-0184": {"TextTiling-w22-k14-m+0.50-n3-s3": [93, 327, 226]}, "interviews:U-0185": {"TextTiling-w22-k14-m+0.50-n3-s3": [427]}, "interviews:U-0186": {"TextTiling-w22-k14-m+0.50-n3-s3": [248, 119, 165]}, "interviews:U-0193": {"TextTiling-w22-k14-m+0.50-n3-s3": [945]}}, "segmentation_type": "linear"}
